LICENSE
README.md
setup.cfg
setup.py
trademaster511/__init__.py
trademaster511.egg-info/PKG-INFO
trademaster511.egg-info/SOURCES.txt
trademaster511.egg-info/dependency_links.txt
trademaster511.egg-info/requires.txt
trademaster511.egg-info/top_level.txt
trademaster511/agents/__init__.py
trademaster511/agents/builder.py
trademaster511/agents/custom.py
trademaster511/agents/algorithmic_trading/__init__.py
trademaster511/agents/algorithmic_trading/dqn.py
trademaster511/agents/high_frequency_trading/__init__.py
trademaster511/agents/high_frequency_trading/ddqn.py
trademaster511/agents/order_execution/__init__.py
trademaster511/agents/order_execution/eteo.py
trademaster511/agents/order_execution/pd.py
trademaster511/agents/portfolio_management/__init__.py
trademaster511/agents/portfolio_management/deeptrader.py
trademaster511/agents/portfolio_management/eiie.py
trademaster511/agents/portfolio_management/investor_imitator.py
trademaster511/collector/__init__.py
trademaster511/collector/binance.py
trademaster511/collector/builder.py
trademaster511/collector/custom.py
trademaster511/collector/helper/__init__.py
trademaster511/collector/helper/celery_app.py
trademaster511/collector/helper/celery_config.py
trademaster511/collector/helper/pika_connection.py
trademaster511/collector/helper/run_celery.py
trademaster511/collector/helper/websocket_consumer.py
trademaster511/collector/helper/websocket_producer.py
trademaster511/datasets/__init__.py
trademaster511/datasets/builder.py
trademaster511/datasets/custom.py
trademaster511/datasets/algorithmic_trading/__init__.py
trademaster511/datasets/algorithmic_trading/dataset.py
trademaster511/datasets/high_frequency_trading/__init__.py
trademaster511/datasets/high_frequency_trading/dataset.py
trademaster511/datasets/order_execution/__init__.py
trademaster511/datasets/order_execution/dataset.py
trademaster511/datasets/portfolio_management/__init__.py
trademaster511/datasets/portfolio_management/dataset.py
trademaster511/environments/__init__.py
trademaster511/environments/builder.py
trademaster511/environments/custom.py
trademaster511/environments/algorithmic_trading/__init__.py
